topsis/__init__.py
topsis/__main__.py
Topsis_Vanshika_102067007-0.5.5.dist-info/LICENSE
Topsis_Vanshika_102067007-0.5.5.dist-info/METADATA
Topsis_Vanshika_102067007-0.5.5.dist-info/WHEEL
Topsis_Vanshika_102067007-0.5.5.dist-info/entry_points.txt
Topsis_Vanshika_102067007-0.5.5.dist-info/top_level.txt
Topsis_Vanshika_102067007-0.5.5.dist-info/RECORD
