Metadata-Version: 2.1
Name: Topsis-Vanshika-102067007
Version: 0.5.5
Summary: This a Topsis package.
Home-page: 
Author: Vanshika Gupta
Author-email: vgupta4_be20@thapar.edu
License-File: LICENSE
Requires-Dist: pandas
Requires-Dist: numpy
